<annotation>
	<folder>train</folder>
	<filename>train_lemon_Image_23.jpg</filename>
	<path>..\image\train_lemon_Image_23.jpg</path>
	<source>
		<database>Unknown</database>
	</source>
	<size>
		<width>230</width>
		<height>234</height>
		<depth>3</depth>
	</size>
	<segmented>0</segmented>
	<object>
		<name>lemon</name>
		<pose>Unspecified</pose>
		<truncated>0</truncated>
		<difficult>0</difficult>
		<bndbox>
			<xmin>7</xmin>
			<ymin>42</ymin>
			<xmax>225</xmax>
			<ymax>205</ymax>
		</bndbox>
	</object>
</annotation>